setup.py
aio_ping/__init__.py
aio_ping.egg-info/PKG-INFO
aio_ping.egg-info/SOURCES.txt
aio_ping.egg-info/dependency_links.txt
aio_ping.egg-info/not-zip-safe
aio_ping.egg-info/top_level.txt
scripts/ping