Metadata-Version: 1.1
Name: aio-ping
Version: 0.1.3
Summary: An async python ICMP ping implementation using raw sockets.
Home-page: https://github.com/M-o-a-T/aioping/
Author: Matthias Urlichs
Author-email: matthias@urlichs.de
License: UNKNOWN
Keywords: asyncio ping icmp network latency
Platform: UNKNOWN
Classifier: Development Status :: 5 - Production/Stable
Classifier: Environment :: Web Environment
Classifier: Intended Audience :: Developers
Classifier: Intended Audience :: Education
Classifier: License :: OSI Approved :: GNU General Public License (GPL)
Classifier: Operating System :: OS Independent
Classifier: Programming Language :: Python
Classifier: Topic :: Internet
Classifier: Topic :: Software Development :: Libraries :: Python Modules
Classifier: Topic :: System :: Networking :: Monitoring
